surrealdb_celery_backend/CLAUDE.md
surrealdb_celery_backend/__init__.py
surrealdb_celery_backend/backend.py
surrealdb_celery_backend-0.3.0.dist-info/METADATA
surrealdb_celery_backend-0.3.0.dist-info/WHEEL
surrealdb_celery_backend-0.3.0.dist-info/licenses/LICENSE
surrealdb_celery_backend-0.3.0.dist-info/RECORD
