Metadata-Version: 2.4
Name: surrealdb-celery-backend
Version: 0.3.0
Summary: Custom Celery result backend for SurrealDB
Project-URL: Homepage, https://github.com/lfnovo/surrealdb-celery-backend
Project-URL: Repository, https://github.com/lfnovo/surrealdb-celery-backend
Project-URL: Issues, https://github.com/lfnovo/surrealdb-celery-backend/issues
Project-URL: Changelog, https://github.com/lfnovo/surrealdb-celery-backend/releases
Author-email: Luis Novo <lfnovo@gmail.com>
Maintainer-email: Luis Novo <lfnovo@gmail.com>
License: MIT
License-File: LICENSE
Keywords: backend,celery,distributed-tasks,result-backend,surrealdb,task-queue
Classifier: Development Status :: 4 - Beta
Classifier: Framework :: Celery
Classifier: Intended Audience :: Developers
Classifier: License :: OSI Approved :: MIT License
Classifier: Operating System :: OS Independent
Classifier: Programming Language :: Python :: 3
Classifier: Programming Language :: Python :: 3.10
Classifier: Programming Language :: Python :: 3.11
Classifier: Programming Language :: Python :: 3.12
Classifier: Topic :: Software Development :: Libraries :: Python Modules
Classifier: Topic :: System :: Distributed Computing
Requires-Python: >=3.10
Requires-Dist: celery>=5.0.0
Requires-Dist: surrealdb>=1.0.0
Provides-Extra: test
Requires-Dist: pytest-mock>=3.0; extra == 'test'
Requires-Dist: pytest>=7.0; extra == 'test'
